traversy/__init__.py
traversy-0.1.32.dist-info/LICENSE.md
traversy-0.1.32.dist-info/WHEEL
traversy-0.1.32.dist-info/METADATA
traversy-0.1.32.dist-info/RECORD
