Metadata-Version: 2.1
Name: traversy
Version: 0.1.32
Summary: Fast data traversal & manipulation tools.
Home-page: https://github.com/tensortom/traversy
License: MIT
Keywords: python,python3,traversal,traverse,recursive,iteration,generator,dict,dictionary,data,mo-dots,dotty_dict,iterate,iterator
Author: Tom A.
Author-email: 14287229+TensorTom@users.noreply.github.com
Requires-Python: >=3.6,<4.0.0
Classifier: License :: OSI Approved :: MIT License
Classifier: Programming Language :: Python :: 3
Classifier: Programming Language :: Python :: 3.6
Classifier: Programming Language :: Python :: 3.7
Classifier: Programming Language :: Python :: 3.8
Classifier: Programming Language :: Python :: 3.9
Requires-Dist: dotty-dict (>=1.3.0)
Requires-Dist: mo-dots (>=3.135.20303)
Project-URL: Documentation, https://tensortom.github.io/traversy/
Project-URL: Repository, https://github.com/tensortom/traversy
